{
    "label": "November Displays",
    "description": "SFF Parents",
    "list": 
  [
{
"label":"Raising Stony Mayhall",
"isbns": [
"9780345522382",
"9780345522375"
]
},
{
"label":"The House in the Cerulean Sea",
"isbns": [
"9781250217288",
"9781250264299",
"9781250217325"
]
},
{
"label":"Snuff",
"isbns": [
"9780792781462",
"9780062011848"
]
},
{
"label":"Sealed",
"isbns": [
"9781789091243"
]
},
{
"label":"The Southern Book Club's Guide to Slaying Vampires",
"isbns": [
"9781683691440",
"9781094136998",
"9781683691433"
]
},
{
"label":"Changes",
"isbns": [
"9780451463173",
"9781101181492"
]
},
{
"label":"The Need",
"isbns": [
"9781982113162"
]
},
{
"label":"Saga",
"isbns": [
"9781607066019"
]
},
{
"label":"Cibola Burn",
"isbns": [
"9780316217620",
"9781478901563"
]
},
{
"label":"A Game of Thrones",
"isbns": [
"9780553897845",
"9780739353370",
"9780307913098",
"9780553103540"
]
},
{
"label":"Oathbringer",
"isbns": [
"9780765326379",
"9781427275936"
]
},
{
"label":"The Reluctant Queen",
"isbns": [
"9780062413352"
]
},
{
"label":"Boy, Snow, Bird",
"isbns": [
"9781594631399"
]
},
{
"label":"The Fifth Season",
"isbns": [
"9780316229302",
"9780316229296"
]
},
{
"label":"The Human Son",
"isbns": [
"9781786183002",
"9781781087886"
]
},
{
"label":"The Runes of the Earth",
"isbns": [
"9780399152320"
]
},
{
"label":"Record of a Spaceborn Few",
"isbns": [
"9780062851154"
]
},
{
"label":"The Song of All",
"isbns": [
"9781597809238"
]
},
{
"label":"The Hills Have Spies",
"isbns": [
"9780756413170",
"9780756413194"
]
},
{
"label":"Nemesis Games",
"isbns": [
"9781478933779",
"9780316217583"
]
}
]
}