{
    "label": "November Displays",
    "description": "Backyard Wildlife",
    "list": 
  [
{
"label":"The Hidden World of the Fox",
"isbns": [
"9780062966100"
]
},
{
"label":"Our Wild Calling",
"isbns": [
"9781616205607",
"9781643750170"
]
},
{
"label":"The Complete Tracker",
"isbns": [
"9781599218588"
]
},
{
"label":"How to Be a Good Creature",
"isbns": [
"9780544938328",
"9781328528230",
"9781684414130",
"9781432858438"
]
},
{
"label":"Eagle's Plume",
"isbns": [
"9780684806969"
]
},
{
"label":"Moose",
"isbns": [
"9781552092552"
]
},
{
"label":"Make a Home for Wildlife",
"isbns": [
"9780811737722"
]
},
{
"label":"Among the Bears",
"isbns": [
"9780805069198"
]
},
{
"label":"American Wolf",
"isbns": [
"9781101902783"
]
},
{
"label":"H Is for Hawk",
"isbns": [
"9780802191670",
"9781481530903",
"9780802123411"
]
},
{
"label":"The Shorebird Guide",
"isbns": [
"9780618432943"
]
},
{
"label":"The Wild out Your Window",
"isbns": [
"9780892725755"
]
},
{
"label":"Bear",
"isbns": [
"9781426211768"
]
},
{
"label":"Drawing Wildlife",
"isbns": [
"9780823023790"
]
},
{
"label":"100 Ways to take better Nature & Wildlife Photographs",
"isbns": [
"9780715331484",
"9781446351918"
]
},
{
"label":"Attracting Birds and Butterflies",
"isbns": [
"9780358106425"
]
},
{
"label":"Black Bears",
"isbns": [
"9780762784936"
]
},
{
"label":"The Company We Keep",
"isbns": [
"9780792233107"
]
},
{
"label":"Wolf Nation",
"isbns": [
"9780306824937"
]
},
{
"label":"Eager: The Surprising, Secret Life of Beavers and Why They Matter",
"isbns": [
"9781603587402",
"9781603587396"
]
},
{
"label":"The Crossley ID Guide: Raptors",
"isbns": [
"9780691157405"
]
},
{
"label":"The Hidden Life of Deer",
"isbns": [
"9780061792106"
]
},
{
"label":"In the Company of Moose",
"isbns": [
"9780811712910"
]
},
{
"label":"Nature Anatomy",
"isbns": [
"9781612122311"
]
},
{
"label":"Return of the Eagle",
"isbns": [
"9781560443001"
]
},
{
"label":"Wildlife Watching in America's National Parks",
"isbns": [
"9781603448147"
]
},
{
"label":"The Hidden Life of Deer",
"isbns": [
"9780061792106"
]
},
{
"label":"A Field Guide to Animal Tracks",
"isbns": [
"9780618517435"
]
}
]
}